odoo/addons/purchase_line_procurement_group/README.rst
odoo/addons/purchase_line_procurement_group/__init__.py
odoo/addons/purchase_line_procurement_group/__manifest__.py
odoo/addons/purchase_line_procurement_group/i18n/fr.po
odoo/addons/purchase_line_procurement_group/i18n/purchase_line_procurement_group.pot
odoo/addons/purchase_line_procurement_group/i18n/zh_CN.po
odoo/addons/purchase_line_procurement_group/models/__init__.py
odoo/addons/purchase_line_procurement_group/models/purchase.py
odoo/addons/purchase_line_procurement_group/models/stock_move.py
odoo/addons/purchase_line_procurement_group/models/stock_rule.py
odoo/addons/purchase_line_procurement_group/readme/CONTRIBUTORS.rst
odoo/addons/purchase_line_procurement_group/readme/CREDITS.rst
odoo/addons/purchase_line_procurement_group/readme/DESCRIPTION.rst
odoo/addons/purchase_line_procurement_group/static/description/icon.png
odoo/addons/purchase_line_procurement_group/static/description/index.html
odoo/addons/purchase_line_procurement_group/tests/__init__.py
odoo/addons/purchase_line_procurement_group/tests/test_po_line_proc_group.py
odoo/addons/purchase_line_procurement_group/views/purchase.xml
odoo13_addon_purchase_line_procurement_group-13.0.1.0.2.dev4.dist-info/METADATA
odoo13_addon_purchase_line_procurement_group-13.0.1.0.2.dev4.dist-info/WHEEL
odoo13_addon_purchase_line_procurement_group-13.0.1.0.2.dev4.dist-info/top_level.txt
odoo13_addon_purchase_line_procurement_group-13.0.1.0.2.dev4.dist-info/RECORD
